tiktok_scraper/__init__.py
tiktok_scraper/cli.py
tiktok_scraper/downloader.py
tiktok_scraper/scrape_utils.py
tiktok_scraper/scraper.py
tiktok_scraper-1.0.3.dist-info/METADATA
tiktok_scraper-1.0.3.dist-info/WHEEL
tiktok_scraper-1.0.3.dist-info/entry_points.txt
tiktok_scraper-1.0.3.dist-info/top_level.txt
tiktok_scraper-1.0.3.dist-info/RECORD
