Metadata-Version: 1.1
Name: tiktok-scraper
Version: 1.0.3
Summary: Scrapes TikTok videos
Home-page: https://github.com/joeyism/tiktok-scraper
Author: joeyism
Author-email: joeyism@gmail.com
License: UNKNOWN
Download-URL: https://github.com/joeyism/tiktok-scraper/archive/1.0.3.tar.gz
Keywords: tik,tok,tiktok,scraper,download,video
Platform: UNKNOWN
